pzSQL/__init__.py
pzSQL/pzSQL.py
pzSQL-0.0.7.7.dist-info/METADATA
pzSQL-0.0.7.7.dist-info/WHEEL
pzSQL-0.0.7.7.dist-info/top_level.txt
pzSQL-0.0.7.7.dist-info/RECORD
